pers/__init__.py
pers/pers.py
pers/version.py
pers-0.2.2.dist-info/LICENSE
pers-0.2.2.dist-info/METADATA
pers-0.2.2.dist-info/WHEEL
pers-0.2.2.dist-info/top_level.txt
pers-0.2.2.dist-info/RECORD
