Metadata-Version: 2.1
Name: pers
Version: 0.2.2
Summary: Persistent results is a Python class that ensures the results of tests will be available even if interruptions during the tests occur.
Home-page: https://github.com/rsusik/pers
Author: Robert Susik
Author-email: robert.susik@gmail.com
License: GPLv3
Classifier: Topic :: Utilities
Classifier: Intended Audience :: Developers
Classifier: Programming Language :: Python
Requires-Python: >=3.8
License-File: LICENSE
Requires-Dist: ncache (==0.3)
